{
	"name": "DS_BLOB_CSV_IN",
	"properties": {
		"linkedServiceName": {
			"referenceName": "LS_BLOB_CSV_IN",
			"type": "LinkedServiceReference"
		},
		"annotations": [],
		"type": "DelimitedText",
		"typeProperties": {
			"location": {
				"type": "AzureBlobStorageLocation",
				"fileName": "customers.csv",
				"container": "customer"
			},
			"columnDelimiter": ",",
			"escapeChar": "\\",
			"firstRowAsHeader": true,
			"quoteChar": "\""
		},
		"schema": [
			{
				"name": "customer_id",
				"type": "String"
			},
			{
				"name": "customer_zip_code_prefix",
				"type": "String"
			},
			{
				"name": "customer_city",
				"type": "String"
			},
			{
				"name": "customer_state",
				"type": "String"
			}
		]
	}
}